Workbook

Sheet Summary
A1: Финансовая модель — сводка
A2: Сравнение сценариев. Поменяйте input в Assumptions — всё пересчитается.
A4: Метрика | B4: Dopamine (Realistic) | C4: Picky (Realistic) | D4: Разница
A5: Downloads year 1 | B5: ='Dopamine — Realistic'!N6 | C5: ='Picky — Realistic'!N6 | D5: =B5-C5
A6: Paying users at M12 | B6: ='Dopamine — Realistic'!M9 | C6: ='Picky — Realistic'!M9 | D6: =B6-C6
A7: MRR at M12 | B7: ='Dopamine — Realistic'!M11 | C7: ='Picky — Realistic'!M11 | D7: =B7-C7
A8: ARR (×12) | B8: ='Dopamine — Realistic'!M11*12 | C8: ='Picky — Realistic'!M11*12 | D8: =B8-C8
A9: Revenue year 1 | B9: ='Dopamine — Realistic'!N12 | C9: ='Picky — Realistic'!N12 | D9: =B9-C9
A10: CAC spend year 1 | B10: ='Dopamine — Realistic'!N13 | C10: ='Picky — Realistic'!N13 | D10: =B10-C10
A11: Net cash year 1 | B11: ='Dopamine — Realistic'!N14 | C11: ='Picky — Realistic'!N15 | D11: =B11-C11
A14: Что говорит модель
A15: Dopamine — solo-friendly: низкие издержки, высокий LTV/CAC, но потолок ниже из-за более узкой аудитории и низкой цены.
A16: Picky — выше потолок MRR и контент-moat, но требует RDN-партнёра ($1500/мес fixed) и партнёрства до запуска. Без partnership = риск.
A18: Откройте Assumptions, поменяйте жёлтые ячейки → пересчёт автоматический.

Sheet Assumptions
A1: Financial Model — Assumptions
A2: Edit yellow cells. Three scenarios per product.
A4: Dopamine fasting
A5: Parameter | B5: Pessimistic | C5: Realistic | D5: Optimistic
A6: Month 1 installs | B6: 200 | C6: 500 | D6: 1000
A7: Monthly install growth rate | B7: 0.2 | C7: 0.4 | D7: 0.6
A8: Install → trial start (after Family Controls auth) | B8: 0.1 | C8: 0.15 | D8: 0.2
A9: Trial → paid conversion | B9: 0.2 | C9: 0.3 | D9: 0.4
A10: Annual subscriber share (vs monthly) | B10: 0.5 | C10: 0.6 | D10: 0.7
A11: Monthly subscription price ($) | B11: 5.99 | C11: 5.99 | D11: 5.99
A12: Annual subscription price ($) | B12: 39.99 | C12: 39.99 | D12: 39.99
A13: Monthly churn (paying users) | B13: 0.1 | C13: 0.06 | D13: 0.04
A14: Blended CAC per paid user ($) | B14: 40 | C14: 15 | D14: 5
A17: Picky eater toddler
A18: Parameter | B18: Pessimistic | C18: Realistic | D18: Optimistic
A19: Month 1 installs | B19: 100 | C19: 300 | D19: 600
A20: Monthly install growth rate | B20: 0.2 | C20: 0.35 | D20: 0.5
A21: Install → trial start | B21: 0.2 | C21: 0.25 | D21: 0.3
A22: Trial → paid conversion | B22: 0.2 | C22: 0.25 | D22: 0.35
A23: Monthly sub share | B23: 0.5 | C23: 0.5 | D23: 0.4
A24: Annual sub share | B24: 0.35 | C24: 0.35 | D24: 0.4
A25: Family sub share | B25: 0.15 | C25: 0.15 | D25: 0.2
A26: Monthly subscription ($) | B26: 9.99 | C26: 9.99 | D26: 9.99
A27: Annual subscription ($/yr) | B27: 59 | C27: 59 | D27: 59
A28: Family monthly ($) | B28: 14.99 | C28: 14.99 | D28: 14.99
A29: Monthly churn (paying) | B29: 0.15 | C29: 0.1 | D29: 0.07
A30: Blended CAC per paid user ($) | B30: 100 | C30: 45 | D30: 20
... A32: Fixed monthly costs — infrastructure ($) | B32: 300 | C32: 300 | D32: 300
A36: Legend:
A37: Yellow — input (edit me)
A38: Gray — calculated (don't edit)

Sheet Dopamine — Realistic
A1: Dopamine fasting — 12-month projection (Realistic scenario)
A2: Change scenario by editing formulas (default reads from Assumptions col C). Inputs in Assumptions sheet.
A4: Metric | B4: M1 | C4: M2 | D4: M3 | E4: M4 | F4: M5 | G4: M6 | H4: M7 | I4: M8 | J4: M9 | K4: M10 | L4: M11 | M4: M12 | N4: Year
A5: Monthly installs | B5: =Assumptions!C6 | C5: =B5*(1+Assumptions!C7) | D5: =C5*(1+Assumptions!C7) | E5: =D5*(1+Assumptions!C7) | F5: =E5*(1+Assumptions!C7) | G5: =F5*(1+Assumptions!C7) | H5: =G5*(1+Assumptions!C7) | I5: =H5*(1+Assumptions!C7) | J5: =I5*(1+Assumptions!C7) | K5: =J5*(1+Assumptions!C7) | L5: =K5*(1+Assumptions!C7) | M5: =L5*(1+Assumptions!C7) | N5: =SUM(B5:M5)
A6: Cumulative installs | B6: =B5 | C6: =B6+C5 | D6: =C6+D5 | E6: =D6+E5 | F6: =E6+F5 | G6: =F6+G5 | H6: =G6+H5 | I6: =H6+I5 | J6: =I6+J5 | ... M6: =L6+M5 | N6: =M6
A7: Trials started | B7: =B5*Assumptions!C8 | C7: =C5*Assumptions!C8 | D7: =D5*Assumptions!C8 | E7: =E5*Assumptions!C8 | F7: =F5*Assumptions!C8 | G7: =G5*Assumptions!C8 | H7: =H5*Assumptions!C8 | I7: =I5*Assumptions!C8 | J7: =J5*Assumptions!C8 | K7: =K5*Assumptions!C8 | L7: =L5*Assumptions!C8 | M7: =M5*Assumptions!C8 | N7: =SUM(B7:M7)
A8: New paying this month | B8: =B7*Assumptions!C9 | C8: =C7*Assumptions!C9 | D8: =D7*Assumptions!C9 | E8: =E7*Assumptions!C9 | F8: =F7*Assumptions!C9 | G8: =G7*Assumptions!C9 | H8: =H7*Assumptions!C9 | I8: =I7*Assumptions!C9 | J8: =J7*Assumptions!C9 | K8: =K7*Assumptions!C9 | L8: =L7*Assumptions!C9 | M8: =M7*Assumptions!C9 | N8: =SUM(B8:M8)
A9: Active paying users (after churn) | B9: =B8 | C9: =B9*(1-Assumptions!C13)+C8 | D9: =C9*(1-Assumptions!C13)+D8 | E9: =D9*(1-Assumptions!C13)+E8 | F9: =E9*(1-Assumptions!C13)+F8 | G9: =F9*(1-Assumptions!C13)+G8 | H9: =G9*(1-Assumptions!C13)+H8 | I9: =H9*(1-Assumptions!C13)+I8 | J9: =I9*(1-Assumptions!C13)+J8 | K9: =J9*(1-Assumptions!C13)+K8 | L9: =K9*(1-Assumptions!C13)+L8 | M9: =L9*(1-Assumptions!C13)+M8 | N9: =M9
A10: ARPU per paying user / mo ($) | B10: =Assumptions!C10*(Assumptions!C12/12)+(1-Assumptions!C10)*Assumptions!C11 | C10: =Assumptions!C10*(Assumptions!C12/12)+(1-Assumptions!C10)*Assumptions!C11 | D10: =Assumptions!C10*(Assumptions!C12/12)+(1-Assumptions!C10)*Assumptions!C11 | E10: =Assumptions!C10*(Assumptions!C12/12)+(1-Assumptions!C10)*Assumptions!C11 | F10: =Assumptions!C10*(Assumptions!C12/12)+(1-Assumptions!C10)*Assumptions!C11 | G10: =Assumptions!C10*(Assumptions!C12/12)+(1-Assumptions!C10)*Assumptions!C11 | H10: =Assumptions!C10*(Assumptions!C12/12)+(1-Assumptions!C10)*Assumptions!C11 | I10: =Assumptions!C10*(Assumptions!C12/12)+(1-Assumptions!C10)*Assumptions!C11 | J10: =Assumptions!C10*(Assumptions!C12/12)+(1-Assumptions!C10)*Assumptions!C11 | K10: =Assumptions!C10*(Assumptions!C12/12)+(1-Assumptions!C10)*Assumptions!C11 | L10: =Assumptions!C10*(Assumptions!C12/12)+(1-Assumptions!C10)*Assumptions!C11 | M10: =Assumptions!C10*(Assumptions!C12/12)+(1-Assumptions!C10)*Assumptions!C11 | N10: =M10
A11: MRR ($) | B11: =B9*B10 | C11: =C9*C10 | D11: =D9*D10 | E11: =E9*E10 | F11: =F9*F10 | G11: =G9*G10 | H11: =H9*H10 | I11: =I9*I10 | ... M11: =M9*M10 | N11: =M11
A12: Monthly revenue ($) | B12: =B11 | C12: =C11 | D12: =D11 | E12: =E11 | F12: =F11 | G12: =G11 | H12: =H11 | I12: =I11 | ... M12: =M11 | N12: =SUM(B12:M12)
A13: CAC spend ($) | B13: =B8*Assumptions!C14 | C13: =C8*Assumptions!C14 | D13: =D8*Assumptions!C14 | E13: =E8*Assumptions!C14 | F13: =F8*Assumptions!C14 | G13: =G8*Assumptions!C14 | H13: =H8*Assumptions!C14 | I13: =I8*Assumptions!C14 | J13: =J8*Assumptions!C14 | K13: =K8*Assumptions!C14 | L13: =L8*Assumptions!C14 | M13: =M8*Assumptions!C14 | N13: =SUM(B13:M13)
A14: Net cash flow ($) | B14: =B12-B13 | C14: =C12-C13 | D14: =D12-D13 | E14: =E12-E13 | F14: =F12-F13 | G14: =G12-G13 | H14: =H12-H13 | I14: =I12-I13 | ... M14: =M12-M13 | N14: =SUM(B14:M14)
A15: Cumulative cash ($) | B15: =B14 | C15: =B15+C14 | D15: =C15+D14 | E15: =D15+E14 | F15: =E15+F14 | G15: =F15+G14 | H15: =G15+H14 | I15: =H15+I14 | J15: =I15+J14 | ... M15: =L15+M14 | N15: =M15
A18: Year-end snapshot
A19: Total downloads | B19: =N6
A20: Active paying users | B20: =M9
A21: MRR at month 12 | B21: =M11
A22: ARR (MRR × 12) | B22: =B21*12
A23: Total revenue year 1 | B23: =N12
A24: Total CAC spend | B24: =N13
A25: Net cash year 1 | B25: =N14

Sheet Picky — Realistic
A1: Picky eater — 12-month projection (Realistic scenario)
A2: Change scenario by editing formulas (default reads from Assumptions col C). Inputs in Assumptions sheet.
A4: Metric | B4: M1 | C4: M2 | D4: M3 | E4: M4 | F4: M5 | G4: M6 | H4: M7 | I4: M8 | J4: M9 | K4: M10 | L4: M11 | M4: M12 | N4: Year
A5: Monthly installs | B5: =Assumptions!C19 | C5: =B5*(1+Assumptions!C20) | D5: =C5*(1+Assumptions!C20) | E5: =D5*(1+Assumptions!C20) | F5: =E5*(1+Assumptions!C20) | G5: =F5*(1+Assumptions!C20) | H5: =G5*(1+Assumptions!C20) | I5: =H5*(1+Assumptions!C20) | J5: =I5*(1+Assumptions!C20) | K5: =J5*(1+Assumptions!C20) | L5: =K5*(1+Assumptions!C20) | M5: =L5*(1+Assumptions!C20) | N5: =SUM(B5:M5)
A6: Cumulative installs | B6: =B5 | C6: =B6+C5 | D6: =C6+D5 | E6: =D6+E5 | F6: =E6+F5 | G6: =F6+G5 | H6: =G6+H5 | I6: =H6+I5 | J6: =I6+J5 | ... M6: =L6+M5 | N6: =M6
A7: Trials started | B7: =B5*Assumptions!C21 | C7: =C5*Assumptions!C21 | D7: =D5*Assumptions!C21 | E7: =E5*Assumptions!C21 | F7: =F5*Assumptions!C21 | G7: =G5*Assumptions!C21 | H7: =H5*Assumptions!C21 | I7: =I5*Assumptions!C21 | J7: =J5*Assumptions!C21 | K7: =K5*Assumptions!C21 | L7: =L5*Assumptions!C21 | M7: =M5*Assumptions!C21 | N7: =SUM(B7:M7)
A8: New paying this month | B8: =B7*Assumptions!C22 | C8: =C7*Assumptions!C22 | D8: =D7*Assumptions!C22 | E8: =E7*Assumptions!C22 | F8: =F7*Assumptions!C22 | G8: =G7*Assumptions!C22 | H8: =H7*Assumptions!C22 | I8: =I7*Assumptions!C22 | J8: =J7*Assumptions!C22 | K8: =K7*Assumptions!C22 | L8: =L7*Assumptions!C22 | M8: =M7*Assumptions!C22 | N8: =SUM(B8:M8)
A9: Active paying users (after churn) | B9: =B8 | C9: =B9*(1-Assumptions!C29)+C8 | D9: =C9*(1-Assumptions!C29)+D8 | E9: =D9*(1-Assumptions!C29)+E8 | F9: =E9*(1-Assumptions!C29)+F8 | G9: =F9*(1-Assumptions!C29)+G8 | H9: =G9*(1-Assumptions!C29)+H8 | I9: =H9*(1-Assumptions!C29)+I8 | J9: =I9*(1-Assumptions!C29)+J8 | K9: =J9*(1-Assumptions!C29)+K8 | L9: =K9*(1-Assumptions!C29)+L8 | M9: =L9*(1-Assumptions!C29)+M8 | N9: =M9
A10: ARPU per paying user / mo ($) | B10: =Assumptions!C23*Assumptions!C26+Assumptions!C24*(Assumptions!C27/12)+Assumptions!C25*Assumptions!C28 | C10: =Assumptions!C23*Assumptions!C26+Assumptions!C24*(Assumptions!C27/12)+Assumptions!C25*Assumptions!C28 | D10: =Assumptions!C23*Assumptions!C26+Assumptions!C24*(Assumptions!C27/12)+Assumptions!C25*Assumptions!C28 | E10: =Assumptions!C23*Assumptions!C26+Assumptions!C24*(Assumptions!C27/12)+Assumptions!C25*Assumptions!C28 | F10: =Assumptions!C23*Assumptions!C26+Assumptions!C24*(Assumptions!C27/12)+Assumptions!C25*Assumptions!C28 | G10: =Assumptions!C23*Assumptions!C26+Assumptions!C24*(Assumptions!C27/12)+Assumptions!C25*Assumptions!C28 | H10: =Assumptions!C23*Assumptions!C26+Assumptions!C24*(Assumptions!C27/12)+Assumptions!C25*Assumptions!C28 | I10: =Assumptions!C23*Assumptions!C26+Assumptions!C24*(Assumptions!C27/12)+Assumptions!C25*Assumptions!C28 | J10: =Assumptions!C23*Assumptions!C26+Assumptions!C24*(Assumptions!C27/12)+Assumptions!C25*Assumptions!C28 | K10: =Assumptions!C23*Assumptions!C26+Assumptions!C24*(Assumptions!C27/12)+Assumptions!C25*Assumptions!C28 | L10: =Assumptions!C23*Assumptions!C26+Assumptions!C24*(Assumptions!C27/12)+Assumptions!C25*Assumptions!C28 | M10: =Assumptions!C23*Assumptions!C26+Assumptions!C24*(Assumptions!C27/12)+Assumptions!C25*Assumptions!C28 | N10: =M10
A11: MRR ($) | B11: =B9*B10 | C11: =C9*C10 | D11: =D9*D10 | E11: =E9*E10 | F11: =F9*F10 | G11: =G9*G10 | H11: =H9*H10 | I11: =I9*I10 | ... M11: =M9*M10 | N11: =M11
A12: Monthly revenue ($) | B12: =B11 | C12: =C11 | D12: =D11 | E12: =E11 | F12: =F11 | G12: =G11 | H12: =H11 | I12: =I11 | ... M12: =M11 | N12: =SUM(B12:M12)
A13: CAC spend ($) | B13: =B8*Assumptions!C30 | C13: =C8*Assumptions!C30 | D13: =D8*Assumptions!C30 | E13: =E8*Assumptions!C30 | F13: =F8*Assumptions!C30 | G13: =G8*Assumptions!C30 | H13: =H8*Assumptions!C30 | I13: =I8*Assumptions!C30 | J13: =J8*Assumptions!C30 | K13: =K8*Assumptions!C30 | L13: =L8*Assumptions!C30 | M13: =M8*Assumptions!C30 | N13: =SUM(B13:M13)
A14: Fixed monthly costs ($) | B14: =Assumptions!C31+Assumptions!C32 | C14: =Assumptions!C31+Assumptions!C32 | D14: =Assumptions!C31+Assumptions!C32 | E14: =Assumptions!C31+Assumptions!C32 | F14: =Assumptions!C31+Assumptions!C32 | G14: =Assumptions!C31+Assumptions!C32 | H14: =Assumptions!C31+Assumptions!C32 | I14: =Assumptions!C31+Assumptions!C32 | J14: =Assumptions!C31+Assumptions!C32 | K14: =Assumptions!C31+Assumptions!C32 | L14: =Assumptions!C31+Assumptions!C32 | M14: =Assumptions!C31+Assumptions!C32 | N14: =SUM(B14:M14)
A15: Net cash flow ($) | B15: =B12-B13-B14 | C15: =C12-C13-C14 | D15: =D12-D13-D14 | E15: =E12-E13-E14 | F15: =F12-F13-F14 | G15: =G12-G13-G14 | H15: =H12-H13-H14 | I15: =I12-I13-I14 | ... M15: =M12-M13-M14 | N15: =SUM(B15:M15)
A16: Cumulative cash ($) | B16: =B15 | C16: =B16+C15 | D16: =C16+D15 | E16: =D16+E15 | F16: =E16+F15 | G16: =F16+G15 | H16: =G16+H15 | I16: =H16+I15 | J16: =I16+J15 | ... M16: =L16+M15 | N16: =M16
A19: Year-end snapshot
A20: Total downloads | B20: =N6
A21: Active paying users | B21: =M9
A22: MRR at month 12 | B22: =M11
A23: ARR (MRR × 12) | B23: =B22*12
A24: Total revenue year 1 | B24: =N12
A25: Total CAC spend | B25: =N13
A26: Total fixed costs | B26: =N14
A27: Net cash year 1 | B27: =N15
